palisades/README.py
palisades/__init__.py
palisades/__main__.py
palisades/config.env
palisades/env.py
palisades/host.py
palisades/logger.py
palisades/sample.env
palisades/urls.py
palisades/.abcli/abcli.sh
palisades/.abcli/actions.sh
palisades/.abcli/aka.sh
palisades/.abcli/alias.sh
palisades/.abcli/analytics.sh
palisades/.abcli/browse.sh
palisades/.abcli/buildings.sh
palisades/.abcli/install.sh
palisades/.abcli/palisades.sh
palisades/.abcli/analytics/building.sh
palisades/.abcli/analytics/ingest.sh
palisades/.abcli/buildings/analyze.sh
palisades/.abcli/buildings/download_footprints.sh
palisades/.abcli/tests/README.sh
palisades/.abcli/tests/analytics_ingest.sh
palisades/.abcli/tests/analytics_ingest_building.sh
palisades/.abcli/tests/analytics_ingest_building_deep.sh
palisades/.abcli/tests/buildings_analyze.sh
palisades/.abcli/tests/buildings_download_footprints.sh
palisades/.abcli/tests/help.sh
palisades/.abcli/tests/ingest.sh
palisades/.abcli/tests/label.sh
palisades/.abcli/tests/predict.sh
palisades/.abcli/tests/train.sh
palisades/.abcli/tests/version.sh
palisades/.abcli/top/ingest.sh
palisades/.abcli/top/label.sh
palisades/.abcli/top/predict.sh
palisades/.abcli/top/train.sh
palisades/analytics/__init__.py
palisades/analytics/__main__.py
palisades/analytics/building.py
palisades/analytics/collection.py
palisades/analytics/ingest.py
palisades/analytics/logging.py
palisades/buildings/__init__.py
palisades/buildings/__main__.py
palisades/buildings/analysis.py
palisades/geo/__init__.py
palisades/geo/dataset.py
palisades/help/__init__.py
palisades/help/__main__.py
palisades/help/analytics.py
palisades/help/buildings.py
palisades/help/functions.py
palisades/semseg/__init__.py
palisades/semseg/__main__.py
palisades/semseg/predict.py
palisades/workflow/__init__.py
palisades/workflow/__main__.py
palisades/workflow/ingest.py
palisades-4.345.1.dist-info/LICENSE
palisades-4.345.1.dist-info/METADATA
palisades-4.345.1.dist-info/WHEEL
palisades-4.345.1.dist-info/top_level.txt
palisades-4.345.1.dist-info/RECORD
