Metadata-Version: 2.2
Name: palisades
Version: 4.345.1
Summary: 🧑🏽‍🚒 Post-Disaster Land Cover Classification.
Home-page: https://github.com/kamangir/palisades
Author: Arash Abadpour (Kamangir)
Author-email: arash@kamangir.net
License: Public Domain
Classifier: Programming Language :: Python :: 3
Classifier: Programming Language :: Unix Shell
Classifier: License :: Public Domain
Classifier: Operating System :: OS Independent
License-File: LICENSE
Requires-Dist: blue_geo
Requires-Dist: roofai
Requires-Dist: fiona
Requires-Dist: osmnx
Requires-Dist: pyproj
Requires-Dist: dask_geopandas
Requires-Dist: deltalake
Requires-Dist: mercantile
Requires-Dist: planetary_computer
Requires-Dist: s3fs
Requires-Dist: adlfs
Dynamic: author
Dynamic: author-email
Dynamic: classifier
Dynamic: description
Dynamic: description-content-type
Dynamic: home-page
Dynamic: license
Dynamic: requires-dist
Dynamic: summary
